only_train_once/__init__.py
only_train_once/assets/__init__.py
only_train_once/assets/theme.py
only_train_once/dependency_graph/__init__.py
only_train_once/dependency_graph/pruning_dependency.py
only_train_once/flops/__init__.py
only_train_once/flops/flops.py
only_train_once/graph/__init__.py
only_train_once/graph/graph.py
only_train_once/graph/node.py
only_train_once/graph/node_group.py
only_train_once/graph/utils.py
only_train_once/operation/__init__.py
only_train_once/operation/operator.py
only_train_once/optimizer/__init__.py
only_train_once/optimizer/hesso.py
only_train_once/optimizer/hyperparameter.py
only_train_once/optimizer/importance_score/__init__.py
only_train_once/optimizer/importance_score/cosine_similarity.py
only_train_once/optimizer/importance_score/magnitude.py
only_train_once/optimizer/importance_score/taylor.py
only_train_once/subnet_construction/__init__.py
only_train_once/subnet_construction/pruning_compression.py
only_train_once/transform/__init__.py
only_train_once/transform/ge.py
only_train_once/transform/graph_transform.py
only_train_once/transform/tensor_transform.py
only_train_once-3.0.1.dist-info/LICENSE
only_train_once-3.0.1.dist-info/METADATA
only_train_once-3.0.1.dist-info/WHEEL
only_train_once-3.0.1.dist-info/top_level.txt
only_train_once-3.0.1.dist-info/RECORD
