Metadata-Version: 2.1
Name: only-train-once
Version: 3.0.1
Summary: Only Train Once (OTO): Automatic One-Shot General DNN Training and Compression Framework
Home-page: https://github.com/tianyic/only_train_once
Author: Tianyi Chen
Author-email: tiachen@microsoft.com
License: MIT
Keywords: automatic,one-shot,structure pruning,sparse optimization
Classifier: Development Status :: 3 - Alpha
Classifier: Intended Audience :: Developers
Classifier: License :: OSI Approved :: MIT License
Classifier: Programming Language :: Python :: 3
License-File: LICENSE
Requires-Dist: numpy
Requires-Dist: graphviz
Requires-Dist: pydot
Requires-Dist: onnx
